MANIFEST.in
setup.py
bin/spats_tool
spats_shape_seq/__init__.py
spats_shape_seq/counters.py
spats_shape_seq/db.py
spats_shape_seq/diagram.py
spats_shape_seq/experiment.py
spats_shape_seq/lookup.py
spats_shape_seq/mask.py
spats_shape_seq/matrix.py
spats_shape_seq/native.py
spats_shape_seq/nb.py
spats_shape_seq/nbutil.py
spats_shape_seq/pair.py
spats_shape_seq/parse.py
spats_shape_seq/partial.py
spats_shape_seq/plots.py
spats_shape_seq/processor.py
spats_shape_seq/profiles.py
spats_shape_seq/reads.py
spats_shape_seq/run.py
spats_shape_seq/sequence.py
spats_shape_seq/spats.py
spats_shape_seq/tag.py
spats_shape_seq/target.py
spats_shape_seq/tool.py
spats_shape_seq/util.py
spats_shape_seq/worker.py
spats_shape_seq.egg-info/PKG-INFO
spats_shape_seq.egg-info/SOURCES.txt
spats_shape_seq.egg-info/dependency_links.txt
spats_shape_seq.egg-info/not-zip-safe
spats_shape_seq.egg-info/top_level.txt
spats_shape_seq/static/main.js
spats_shape_seq/static/main.js~
spats_shape_seq/static/styles/fsa.mplstyle