Metadata-Version: 1.2
Name: spats-shape-seq
Version: 1.9.37
Summary: The Spats package implements a read mapping and reactivity analysis pipeline for calculating SHAPE-Seq reactivities from an input set of next-generation reads.
Home-page: http://luckslab.github.io/spats
Author: LucksLab
Author-email: spats.shape@gmail.com
License: MIT
Keywords: spats
Platform: UNKNOWN
Classifier: Development Status :: 5 - Production/Stable
Classifier: License :: OSI Approved :: Boost Software License 1.0 (BSL-1.0)
Classifier: Programming Language :: Python :: 2.7
Requires-Python: <3
